Metadata-Version: 1.0
Name: vinpack
Version: 2.0.3
Summary: The module vinpack.dateutils has a print_cal() function along with few other.
Home-page: http://vinod.co
Author: Vinod
Author-email: vinod@vinod.co
License: MIT
Platform: UNKNOWN
